{
    "cards": [
        {
            "id":0,
            "number":"0",
            "name":"The Fool",
            "keywords":["fool"],
            "description":"Igor",
            "image":"https://static.wikia.nocookie.net/megamitensei/images/5/53/Fool-0.png"
        },

        {
            "id":1,
            "number":"I",
            "name":"The Magician",
            "keywords":["magician", "magic"],
            "description":"Morgana",
            "image":"https://static.wikia.nocookie.net/megamitensei/images/c/cb/Magician-0.png"
        },

        {
            "id":2,
            "number":"II",
            "name":"The Priestess",
            "keywords":["priestess"],
            "description":"Makoto Niijima",
            "image":"https://static.wikia.nocookie.net/megamitensei/images/a/ad/Priestess-0.png"
        },

        {
            "id":3,
            "number":"III",
            "name":"The Empress",
            "keywords":["empress"],
            "description":"Haru Okumura",
            "image":"https://static.wikia.nocookie.net/megamitensei/images/6/63/Empress-0.png"
        },

        {
            "id":4,
            "number":"IV",
            "name":"The Emperor",
            "keywords":["emperor"],
            "description":"Yusuke Kitagawa",
            "image":"https://static.wikia.nocookie.net/megamitensei/images/e/e6/Emperor-0.png"
        },

        {
            "id":5,
            "number":"V",
            "name":"The Hierophant",
            "keywords":["hierophant"],
            "description":"Sojiro Sakura",
            "image":"https://static.wikia.nocookie.net/megamitensei/images/f/f6/Hierophant-0.png"
        },

        {
            "id":6,
            "number":"VI",
            "name":"The Lovers",
            "keywords":["lovers"],
            "description":"Ann Takamaki",
            "image":"https://static.wikia.nocookie.net/megamitensei/images/a/a5/Lovers-0.png"
        },

        {
            "id":7,
            "number":"VII",
            "name":"The Chariot",
            "keywords":["chariot"],
            "description":"Ryuji Sakamoto",
            "image":"https://static.wikia.nocookie.net/megamitensei/images/1/15/Chariot-0.png"
        },

        {
            "id":8,
            "number":"VIII",
            "name":"Justice",
            "keywords":["justice"],
            "description":"Goro Akechi",
            "image":"https://static.wikia.nocookie.net/megamitensei/images/8/83/Justice-0.png"
        },

        {
            "id":9,
            "number":"IX",
            "name":"The Hermit",
            "keywords":["hermit"],
            "description":"Futaba Sakura",
            "image":"https://static.wikia.nocookie.net/megamitensei/images/a/ab/Hermit-0.png"
        },

        {
            "id":10,
            "number":"X",
            "name":"The Wheel of Fortune",
            "keywords":["wheel", "fortune"],
            "description":"Chihaya Mifune",
            "image":"https://static.wikia.nocookie.net/megamitensei/images/f/f3/Fortune-0.png"
        },

        {
            "id":11,
            "number":"XI",
            "name":"Strength",
            "keywords":["strength"],
            "description":"Caroline and Justine",
            "image":"https://static.wikia.nocookie.net/megamitensei/images/b/b0/Strength-0.png"
        },

        {
            "id":12,
            "number":"XII",
            "name":"The Hanged Man",
            "keywords":["hanged", "man"],
            "description":"Munehisa Iwai",
            "image":"https://static.wikia.nocookie.net/megamitensei/images/2/2f/Hanged_Man.png"
        },

        {
            "id":13,
            "number":"XIII",
            "name":"Death",
            "keywords":["death"],
            "description":"Tae Takemi",
            "image":"https://static.wikia.nocookie.net/megamitensei/images/d/df/Death-0.png"
        },

        {
            "id":14,
            "number":"XIV",
            "name":"Temperance",
            "keywords":["temperance"],
            "description":"Sadayo Kawakami",
            "image":"https://static.wikia.nocookie.net/megamitensei/images/2/2d/Temperance-0.png"
        },

        {
            "id":15,
            "number":"XV",
            "name":"The Devil",
            "keywords":["devil"],
            "description":"Ichiko Ohya",
            "image":"https://static.wikia.nocookie.net/megamitensei/images/4/4b/Devil-0.png"
        },

        {
            "id":16,
            "number":"XVI",
            "name":"The Tower",
            "keywords":["tower"],
            "description":"Shinya Oda",
            "image":"https://static.wikia.nocookie.net/megamitensei/images/1/1f/Tower-0.png"
        },

        {
            "id":17,
            "number":"XVII",
            "name":"The Star",
            "keywords":["star"],
            "description":"Hifumi Togo",
            "image":"https://static.wikia.nocookie.net/megamitensei/images/1/15/Star-0.png"
        },

        {
            "id":18,
            "number":"XVIII",
            "name":"The Moon",
            "keywords":["moon"],
            "description":"Yuuki Mishima",
            "image":"https://static.wikia.nocookie.net/megamitensei/images/c/ce/Moon-0.png"
        },

        {
            "id":19,
            "number":"XIX",
            "name":"The Sun",
            "keywords":["sun"],
            "description":"Toranosuke Yoshida",
            "image":"https://static.wikia.nocookie.net/megamitensei/images/f/ff/Sun-0.png"
        },

        {
            "id":20,
            "number":"XX",
            "name":"Judgement",
            "keywords":["judgement","judgment"],
            "description":"Sae Niijima",
            "image":"https://static.wikia.nocookie.net/megamitensei/images/b/b0/Judgement.png"
        },

        {
            "id":21,
            "number":"XXI",
            "name":"The World",
            "keywords":["world"],
            "description":"Ren Amamiya",
            "image":"https://static.wikia.nocookie.net/megamitensei/images/a/a9/World-0.png"
        }
    ]
}